sysinfor/__init__.py
sysinfor/sysinfor.py
tests/__init__.py
tests/test_info.py
sysinfor-0.0.4.dist-info/LICENSE
sysinfor-0.0.4.dist-info/METADATA
sysinfor-0.0.4.dist-info/WHEEL
sysinfor-0.0.4.dist-info/entry_points.txt
sysinfor-0.0.4.dist-info/top_level.txt
sysinfor-0.0.4.dist-info/RECORD
