Metadata-Version: 2.1
Name: sysinfor
Version: 0.0.4
Summary: The package of **SysInfor** is use to collect & manipulate system information for human friendly manner.
Author: Tharanga Jayasinghe
Author-email: nteeje@gmail.com
License-File: LICENSE
Requires-Dist: psutil
Requires-Dist: click
Requires-Dist: datetime
